[
    {
        "q": 0.6408852,
        "pmin": 3.23786375,
        "pmax": 43.54922743,
        "zmin": -77.15465801,
        "zmax": 317.30140962,
        "lapse": 4.48389655,
        "esia": 3,
        "essa": 1,
        "thkRMSE": 194.746,
        "velmagRMSE": 167.718,
        "mixRMSE": 362.464
    },
    {
        "q": 0.95888954,
        "pmin": 9.26457411,
        "pmax": 39.08296529,
        "zmin": -719.65274872,
        "zmax": 695.95321582,
        "lapse": 4.02330678,
        "esia": 3,
        "essa": 1,
        "thkRMSE": 181.217,
        "velmagRMSE": 77.5146,
        "mixRMSE": 258.7316
    },
    {
        "q": 0.46804744,
        "pmin": 12.09401727,
        "pmax": 35.29793142,
        "zmin": -307.10376902,
        "zmax": 775.97945316,
        "lapse": 1.06786612,
        "esia": 3,
        "essa": 1,
        "thkRMSE": 217.853,
        "velmagRMSE": 111.27,
        "mixRMSE": 329.123
    },
    {
        "q": 0.7945214,
        "pmin": 14.1429286,
        "pmax": 38.94170445,
        "zmin": -179.23511178,
        "zmax": 506.7123456,
        "lapse": 1.93941915,
        "esia": 3,
        "essa": 1,
        "thkRMSE": 192.819,
        "velmagRMSE": 76.2673,
        "mixRMSE": 269.0863
    },
    {
        "q": 0.92745329,
        "pmin": 1.92079236,
        "pmax": 39.55843591,
        "zmin": -272.30012459,
        "zmax": 471.22725342,
        "lapse": 3.08606843,
        "esia": 3,
        "essa": 1,
        "thkRMSE": 190.315,
        "velmagRMSE": 80.6871,
        "mixRMSE": 271.0021
    },
    {
        "q": 0.72335652,
        "pmin": 13.14196661,
        "pmax": 44.24205455,
        "zmin": -948.29679957,
        "zmax": 107.49744677,
        "lapse": 3.57588761,
        "esia": 3,
        "essa": 1,
        "thkRMSE": 180.332,
        "velmagRMSE": 77.7342,
        "mixRMSE": 258.0662
    },
    {
        "q": 0.29117854,
        "pmin": 8.87908422,
        "pmax": 40.05986274,
        "zmin": -25.24331149,
        "zmax": 10.51901319,
        "lapse": 1.37346227,
        "esia": 3,
        "essa": 1,
        "thkRMSE": 208.031,
        "velmagRMSE": 173.231,
        "mixRMSE": 381.262
    },
    {
        "q": 0.01531255,
        "pmin": 10.82733063,
        "pmax": 36.24429275,
        "zmin": -963.87117101,
        "zmax": 422.70710207,
        "lapse": 2.10363219,
        "esia": 3,
        "essa": 1,
        "thkRMSE": 209.868,
        "velmagRMSE": 495.397,
        "mixRMSE": 705.265
    },
    {
        "q": 0.83190683,
        "pmin": 3.96244315,
        "pmax": 43.22755127,
        "zmin": -229.24610135,
        "zmax": 268.90744221,
        "lapse": 2.53708874,
        "esia": 3,
        "essa": 1,
        "thkRMSE": 189.263,
        "velmagRMSE": 73.975,
        "mixRMSE": 263.238
    },
    {
        "q": 0.44773937,
        "pmin": 10.19686635,
        "pmax": 37.60949962,
        "zmin": -139.26763337,
        "zmax": 612.03357102,
        "lapse": 3.75668624,
        "esia": 3,
        "essa": 1,
        "thkRMSE": 196.945,
        "velmagRMSE": 167.24,
        "mixRMSE": 364.185
    },
    {
        "q": 0.3359504,
        "pmin": 6.58643595,
        "pmax": 44.92293209,
        "zmin": -414.6838065,
        "zmax": 917.99899487,
        "lapse": 4.56467556,
        "esia": 3,
        "essa": 1,
        "thkRMSE": 194.095,
        "velmagRMSE": 203.913,
        "mixRMSE": 398.00800000000004
    },
    {
        "q": 0.59521873,
        "pmin": 2.78469078,
        "pmax": 41.899948,
        "zmin": -603.54539625,
        "zmax": 831.65131221,
        "lapse": 0.39651075,
        "esia": 3,
        "essa": 1,
        "thkRMSE": 230.416,
        "velmagRMSE": 72.2536,
        "mixRMSE": 302.6696
    },
    {
        "q": 0.69802857,
        "pmin": 4.52515372,
        "pmax": 42.67606538,
        "zmin": -887.44458122,
        "zmax": 219.87566146,
        "lapse": 2.46659973,
        "esia": 3,
        "essa": 1,
        "thkRMSE": 184.442,
        "velmagRMSE": 75.5978,
        "mixRMSE": 260.0398
    },
    {
        "q": 0.54230761,
        "pmin": 1.16185172,
        "pmax": 42.46550503,
        "zmin": -766.12457485,
        "zmax": 92.77376361,
        "lapse": 2.95749898,
        "esia": 3,
        "essa": 1,
        "thkRMSE": 184.551,
        "velmagRMSE": 74.2625,
        "mixRMSE": 258.8135
    },
    {
        "q": 0.35930034,
        "pmin": 11.28194105,
        "pmax": 38.10953876,
        "zmin": -573.797983,
        "zmax": 573.26752882,
        "lapse": 3.45828354,
        "esia": 3,
        "essa": 1,
        "thkRMSE": 190.988,
        "velmagRMSE": 129.462,
        "mixRMSE": 320.45
    },
    {
        "q": 0.05663671,
        "pmin": 0.21699442,
        "pmax": 41.49092891,
        "zmin": -822.45478363,
        "zmax": 952.97650981,
        "lapse": 0.07679969,
        "esia": 3,
        "essa": 1,
        "thkRMSE": 287.645,
        "velmagRMSE": 312.921,
        "mixRMSE": 600.566
    },
    {
        "q": 0.1324912,
        "pmin": 5.3472646,
        "pmax": 40.89197059,
        "zmin": -681.38713559,
        "zmax": 169.25254233,
        "lapse": 1.5788401,
        "esia": 3,
        "essa": 1,
        "thkRMSE": 200.25,
        "velmagRMSE": 238.711,
        "mixRMSE": 438.961
    },
    {
        "q": 0.20728544,
        "pmin": 14.57215307,
        "pmax": 37.07990354,
        "zmin": -499.09843615,
        "zmax": 700.65792957,
        "lapse": 0.9707023,
        "esia": 3,
        "essa": 1,
        "thkRMSE": 218.953,
        "velmagRMSE": 248.488,
        "mixRMSE": 467.44100000000003
    },
    {
        "q": 0.86236191,
        "pmin": 7.74768279,
        "pmax": 35.99910203,
        "zmin": -542.62514027,
        "zmax": 399.18282351,
        "lapse": 4.76713253,
        "esia": 3,
        "essa": 1,
        "thkRMSE": 180.532,
        "velmagRMSE": 79.074,
        "mixRMSE": 259.606
    },
    {
        "q": 0.24233104,
        "pmin": 14.21685031,
        "pmax": 43.71092531,
        "zmin": -150.96722448,
        "zmax": 975.45448411,
        "lapse": 3.98663224,
        "esia": 3,
        "essa": 1,
        "thkRMSE": 201.11,
        "velmagRMSE": 318.431,
        "mixRMSE": 519.5409999999999
    },
    {
        "q": 0.40302189,
        "pmin": 0.60866669,
        "pmax": 38.7853439,
        "zmin": -569.21359941,
        "zmax": 367.53843841,
        "lapse": 1.51970871,
        "esia": 3,
        "essa": 1,
        "thkRMSE": 202.059,
        "velmagRMSE": 127.745,
        "mixRMSE": 329.804
    },
    {
        "q": 0.91166679,
        "pmin": 11.96589573,
        "pmax": 42.26557262,
        "zmin": -667.65799276,
        "zmax": 950.65998846,
        "lapse": 3.71832187,
        "esia": 3,
        "essa": 1,
        "thkRMSE": 182.176,
        "velmagRMSE": 76.528,
        "mixRMSE": 258.704
    },
    {
        "q": 0.20508244,
        "pmin": 7.62166106,
        "pmax": 43.59088978,
        "zmin": -943.71809671,
        "zmax": 172.3129061,
        "lapse": 2.50748199,
        "esia": 3,
        "essa": 1,
        "thkRMSE": 189.291,
        "velmagRMSE": 165.709,
        "mixRMSE": 355.0
    },
    {
        "q": 0.61464728,
        "pmin": 1.57994253,
        "pmax": 40.74809413,
        "zmin": -33.75997062,
        "zmax": 84.61422125,
        "lapse": 2.69098899,
        "esia": 3,
        "essa": 1,
        "thkRMSE": 214.329,
        "velmagRMSE": 224.782,
        "mixRMSE": 439.111
    },
    {
        "q": 0.8708767,
        "pmin": 5.29669226,
        "pmax": 40.44323958,
        "zmin": -706.37364864,
        "zmax": 784.10533177,
        "lapse": 0.61483475,
        "esia": 3,
        "essa": 1,
        "thkRMSE": 212.159,
        "velmagRMSE": 72.2449,
        "mixRMSE": 284.4039
    },
    {
        "q": 0.3803944,
        "pmin": 6.40378583,
        "pmax": 38.3345269,
        "zmin": -67.58060157,
        "zmax": 159.9427627,
        "lapse": 2.96721008,
        "esia": 3,
        "essa": 1,
        "thkRMSE": 200.614,
        "velmagRMSE": 171.294,
        "mixRMSE": 371.908
    },
    {
        "q": 0.93609304,
        "pmin": 2.32446437,
        "pmax": 35.17661733,
        "zmin": -796.0593938,
        "zmax": 1.80749765,
        "lapse": 4.95634002,
        "esia": 3,
        "essa": 1,
        "thkRMSE": 178.174,
        "velmagRMSE": 78.4248,
        "mixRMSE": 256.5988
    },
    {
        "q": 0.43702375,
        "pmin": 3.99601938,
        "pmax": 36.98935668,
        "zmin": -296.71021144,
        "zmax": 634.70587259,
        "lapse": 1.36238713,
        "esia": 3,
        "essa": 1,
        "thkRMSE": 226.512,
        "velmagRMSE": 153.685,
        "mixRMSE": 380.197
    },
    {
        "q": 0.85812062,
        "pmin": 14.91572024,
        "pmax": 41.8139922,
        "zmin": -100.97166941,
        "zmax": 818.38351841,
        "lapse": 4.14157249,
        "esia": 3,
        "essa": 1,
        "thkRMSE": 184.192,
        "velmagRMSE": 80.7216,
        "mixRMSE": 264.9136
    },
    {
        "q": 0.25877892,
        "pmin": 8.08142231,
        "pmax": 35.66163745,
        "zmin": -623.45021741,
        "zmax": 234.26725682,
        "lapse": 1.16419881,
        "esia": 3,
        "essa": 1,
        "thkRMSE": 205.872,
        "velmagRMSE": 183.466,
        "mixRMSE": 389.338
    },
    {
        "q": 0.5438751,
        "pmin": 13.67265885,
        "pmax": 40.86052145,
        "zmin": -982.64721232,
        "zmax": 735.77423296,
        "lapse": 0.4280594,
        "esia": 3,
        "essa": 1,
        "thkRMSE": 211.972,
        "velmagRMSE": 74.9259,
        "mixRMSE": 286.8979
    },
    {
        "q": 0.81834513,
        "pmin": 1.57620046,
        "pmax": 39.11877511,
        "zmin": -310.45416029,
        "zmax": 672.80954557,
        "lapse": 4.42481277,
        "esia": 3,
        "essa": 1,
        "thkRMSE": 189.206,
        "velmagRMSE": 95.2642,
        "mixRMSE": 284.4702
    },
    {
        "q": 0.64716279,
        "pmin": 0.48019754,
        "pmax": 39.61144974,
        "zmin": -141.58581694,
        "zmax": 874.28297817,
        "lapse": 2.26014544,
        "esia": 3,
        "essa": 1,
        "thkRMSE": 257.745,
        "velmagRMSE": 338.552,
        "mixRMSE": 596.297
    },
    {
        "q": 0.73034559,
        "pmin": 7.86106994,
        "pmax": 44.69338989,
        "zmin": -938.48070283,
        "zmax": 568.84403263,
        "lapse": 3.37529195,
        "esia": 3,
        "essa": 1,
        "thkRMSE": 182.023,
        "velmagRMSE": 76.5715,
        "mixRMSE": 258.5945
    },
    {
        "q": 0.35556209,
        "pmin": 6.98362722,
        "pmax": 43.39271245,
        "zmin": -516.06267652,
        "zmax": 929.22539368,
        "lapse": 3.27593833,
        "esia": 3,
        "essa": 1,
        "thkRMSE": 197.778,
        "velmagRMSE": 183.961,
        "mixRMSE": 381.73900000000003
    },
    {
        "q": 0.15766876,
        "pmin": 9.5033186,
        "pmax": 40.35605582,
        "zmin": -885.42717193,
        "zmax": 12.0807929,
        "lapse": 4.20329551,
        "esia": 3,
        "essa": 1,
        "thkRMSE": 185.462,
        "velmagRMSE": 238.24,
        "mixRMSE": 423.702
    },
    {
        "q": 0.88824667,
        "pmin": 6.18856051,
        "pmax": 38.21500009,
        "zmin": -418.08152737,
        "zmax": 277.3445094,
        "lapse": 0.71784193,
        "esia": 3,
        "essa": 1,
        "thkRMSE": 204.329,
        "velmagRMSE": 72.6612,
        "mixRMSE": 276.9902
    },
    {
        "q": 0.56331631,
        "pmin": 11.9802304,
        "pmax": 39.33327772,
        "zmin": -458.56758283,
        "zmax": 306.694982,
        "lapse": 0.40623768,
        "esia": 3,
        "essa": 1,
        "thkRMSE": 211.926,
        "velmagRMSE": 72.6864,
        "mixRMSE": 284.6124
    },
    {
        "q": 0.28986546,
        "pmin": 14.59954347,
        "pmax": 41.44947441,
        "zmin": -709.83253517,
        "zmax": 802.75690772,
        "lapse": 3.99997251,
        "esia": 3,
        "essa": 1,
        "thkRMSE": 187.851,
        "velmagRMSE": 174.784,
        "mixRMSE": 362.635
    },
    {
        "q": 0.34443039,
        "pmin": 14.04603388,
        "pmax": 42.02441589,
        "zmin": -853.72502257,
        "zmax": 789.09726359,
        "lapse": 0.25169745,
        "esia": 3,
        "essa": 1,
        "thkRMSE": 222.746,
        "velmagRMSE": 94.2651,
        "mixRMSE": 317.0111
    },
    {
        "q": 0.68693626,
        "pmin": 6.50214026,
        "pmax": 37.36767616,
        "zmin": -391.90517773,
        "zmax": 619.28302054,
        "lapse": 3.78909923,
        "esia": 3,
        "essa": 1,
        "thkRMSE": 187.692,
        "velmagRMSE": 76.8243,
        "mixRMSE": 264.5163
    },
    {
        "q": 0.47089812,
        "pmin": 13.39796698,
        "pmax": 37.62453663,
        "zmin": -950.11371878,
        "zmax": 713.44214266,
        "lapse": 1.62062814,
        "esia": 3,
        "essa": 1,
        "thkRMSE": 204.081,
        "velmagRMSE": 78.132,
        "mixRMSE": 282.21299999999997
    },
    {
        "q": 0.95261115,
        "pmin": 2.03070578,
        "pmax": 37.12631248,
        "zmin": -350.97688144,
        "zmax": 528.91818155,
        "lapse": 4.60036908,
        "esia": 3,
        "essa": 1,
        "thkRMSE": 184.387,
        "velmagRMSE": 79.9942,
        "mixRMSE": 264.38120000000004
    },
    {
        "q": 0.97060171,
        "pmin": 0.83849166,
        "pmax": 37.33151557,
        "zmin": -70.74250156,
        "zmax": 25.15214842,
        "lapse": 2.53400482,
        "esia": 3,
        "essa": 1,
        "thkRMSE": 194.095,
        "velmagRMSE": 203.913,
        "mixRMSE": 398.00800000000004
    },
    {
        "q": 0.51410038,
        "pmin": 5.21060835,
        "pmax": 41.86794015,
        "zmin": -828.45310656,
        "zmax": 616.57507408,
        "lapse": 1.94717815,
        "esia": 3,
        "essa": 1,
        "thkRMSE": 192.716,
        "velmagRMSE": 74.2846,
        "mixRMSE": 267.0006
    },
    {
        "q": 0.67626186,
        "pmin": 8.40671921,
        "pmax": 36.19555838,
        "zmin": -39.3375985,
        "zmax": 139.01903914,
        "lapse": 4.97032327,
        "esia": 3,
        "essa": 1,
        "thkRMSE": 184.978,
        "velmagRMSE": 92.1368,
        "mixRMSE": 277.1148
    },
    {
        "q": 0.13326866,
        "pmin": 3.3603908,
        "pmax": 43.62360675,
        "zmin": -673.04395912,
        "zmax": 413.66202872,
        "lapse": 1.18884905,
        "esia": 3,
        "essa": 1,
        "thkRMSE": 206.626,
        "velmagRMSE": 246.903,
        "mixRMSE": 453.529
    },
    {
        "q": 0.03327427,
        "pmin": 10.35129584,
        "pmax": 42.98057614,
        "zmin": -449.37120449,
        "zmax": 37.00888921,
        "lapse": 2.23363672,
        "esia": 3,
        "essa": 1,
        "thkRMSE": 194.078,
        "velmagRMSE": 260.915,
        "mixRMSE": 454.99300000000005
    },
    {
        "q": 0.6247508,
        "pmin": 12.43006494,
        "pmax": 44.18618015,
        "zmin": -665.68262002,
        "zmax": 963.40424638,
        "lapse": 1.26730455,
        "esia": 3,
        "essa": 1,
        "thkRMSE": 198.605,
        "velmagRMSE": 73.587,
        "mixRMSE": 272.192
    },
    {
        "q": 0.5193621,
        "pmin": 8.9421021,
        "pmax": 37.70421187,
        "zmin": -548.5011432,
        "zmax": 898.72167785,
        "lapse": 2.64571996,
        "esia": 3,
        "essa": 1,
        "thkRMSE": 194.38,
        "velmagRMSE": 84.2711,
        "mixRMSE": 278.6511
    },
    {
        "q": 0.20041011,
        "pmin": 14.97669041,
        "pmax": 38.64795949,
        "zmin": -730.08697415,
        "zmax": 942.92622702,
        "lapse": 3.64396791,
        "esia": 3,
        "essa": 1,
        "thkRMSE": 194.15,
        "velmagRMSE": 282.209,
        "mixRMSE": 476.35900000000004
    },
    {
        "q": 0.33047048,
        "pmin": 2.62680467,
        "pmax": 41.72269447,
        "zmin": -929.78216565,
        "zmax": 103.46642256,
        "lapse": 2.77254142,
        "esia": 3,
        "essa": 1,
        "thkRMSE": 188.629,
        "velmagRMSE": 93.7585,
        "mixRMSE": 282.3875
    },
    {
        "q": 0.85011629,
        "pmin": 3.78475811,
        "pmax": 41.22798722,
        "zmin": -113.39088518,
        "zmax": 823.97160367,
        "lapse": 4.32530883,
        "esia": 3,
        "essa": 1,
        "thkRMSE": 195.351,
        "velmagRMSE": 112.303,
        "mixRMSE": 307.654
    },
    {
        "q": 0.40470455,
        "pmin": 9.91526219,
        "pmax": 42.33283458,
        "zmin": -766.93747145,
        "zmax": 426.12763591,
        "lapse": 3.86451824,
        "esia": 3,
        "essa": 1,
        "thkRMSE": 185.042,
        "velmagRMSE": 73.8932,
        "mixRMSE": 258.9352
    },
    {
        "q": 0.1974043,
        "pmin": 10.62193914,
        "pmax": 35.75099743,
        "zmin": -472.11192116,
        "zmax": 477.45021251,
        "lapse": 4.09326627,
        "esia": 3,
        "essa": 1,
        "thkRMSE": 194.334,
        "velmagRMSE": 289.027,
        "mixRMSE": 483.361
    },
    {
        "q": 0.80517468,
        "pmin": 6.37890729,
        "pmax": 36.94646779,
        "zmin": -528.59602119,
        "zmax": 228.76703329,
        "lapse": 2.87703636,
        "esia": 3,
        "essa": 1,
        "thkRMSE": 184.458,
        "velmagRMSE": 75.8773,
        "mixRMSE": 260.3353
    },
    {
        "q": 0.24386813,
        "pmin": 12.90052727,
        "pmax": 44.13786651,
        "zmin": -585.39298827,
        "zmax": 62.11907362,
        "lapse": 4.05270484,
        "esia": 3,
        "essa": 1,
        "thkRMSE": 183.789,
        "velmagRMSE": 130.059,
        "mixRMSE": 313.84799999999996
    },
    {
        "q": 0.79651173,
        "pmin": 4.71255044,
        "pmax": 37.92720912,
        "zmin": -251.96033404,
        "zmax": 750.4927352,
        "lapse": 4.53250242,
        "esia": 3,
        "essa": 1,
        "thkRMSE": 187.01,
        "velmagRMSE": 93.4264,
        "mixRMSE": 280.4364
    },
    {
        "q": 0.92150228,
        "pmin": 12.50421146,
        "pmax": 41.00680101,
        "zmin": -183.25701164,
        "zmax": 329.97616219,
        "lapse": 3.53676463,
        "esia": 3,
        "essa": 1,
        "thkRMSE": 183.083,
        "velmagRMSE": 77.8641,
        "mixRMSE": 260.9471
    },
    {
        "q": 0.58055076,
        "pmin": 10.00742983,
        "pmax": 39.93032772,
        "zmin": -873.88343826,
        "zmax": 723.45027226,
        "lapse": 0.6102934,
        "esia": 3,
        "essa": 1,
        "thkRMSE": 209.403,
        "velmagRMSE": 72.1424,
        "mixRMSE": 281.5454
    },
    {
        "q": 0.98493506,
        "pmin": 2.36270256,
        "pmax": 42.75395418,
        "zmin": -199.00859555,
        "zmax": 440.87355202,
        "lapse": 1.76835004,
        "esia": 3,
        "essa": 1,
        "thkRMSE": 200.892,
        "velmagRMSE": 77.5051,
        "mixRMSE": 278.3971
    },
    {
        "q": 0.61220258,
        "pmin": 13.98281109,
        "pmax": 40.14335207,
        "zmin": -274.4380397,
        "zmax": 165.91298069,
        "lapse": 1.02271565,
        "esia": 3,
        "essa": 1,
        "thkRMSE": 195.785,
        "velmagRMSE": 70.7143,
        "mixRMSE": 266.4993
    },
    {
        "q": 0.8435795,
        "pmin": 12.15358876,
        "pmax": 35.40789895,
        "zmin": -10.86414324,
        "zmax": 975.71074926,
        "lapse": 3.49025454,
        "esia": 3,
        "essa": 1,
        "thkRMSE": 191.906,
        "velmagRMSE": 88.6856,
        "mixRMSE": 280.59159999999997
    },
    {
        "q": 0.44326238,
        "pmin": 7.42164143,
        "pmax": 43.07685316,
        "zmin": -245.11257555,
        "zmax": 293.2756346,
        "lapse": 3.24751667,
        "esia": 3,
        "essa": 1,
        "thkRMSE": 189.947,
        "velmagRMSE": 131.372,
        "mixRMSE": 321.319
    },
    {
        "q": 0.6555436,
        "pmin": 5.61976963,
        "pmax": 36.71114666,
        "zmin": -116.74035768,
        "zmax": 333.60897259,
        "lapse": 0.04729563,
        "esia": 3,
        "essa": 1,
        "thkRMSE": 274.548,
        "velmagRMSE": 103.512,
        "mixRMSE": 378.06
    },
    {
        "q": 0.73926075,
        "pmin": 11.55601215,
        "pmax": 44.37537288,
        "zmin": -802.58429603,
        "zmax": 173.27242339,
        "lapse": 1.39715242,
        "esia": 3,
        "essa": 1,
        "thkRMSE": 188.19,
        "velmagRMSE": 75.6546,
        "mixRMSE": 263.8446
    },
    {
        "q": 0.77367724,
        "pmin": 4.82479683,
        "pmax": 36.44380411,
        "zmin": -698.05517804,
        "zmax": 989.60852797,
        "lapse": 0.7667419,
        "esia": 3,
        "essa": 1,
        "thkRMSE": 216.141,
        "velmagRMSE": 74.4,
        "mixRMSE": 290.541
    },
    {
        "q": 0.58398024,
        "pmin": 8.68465547,
        "pmax": 42.63537197,
        "zmin": -551.63510326,
        "zmax": 650.31010011,
        "lapse": 0.13738568,
        "esia": 3,
        "essa": 1,
        "thkRMSE": 231.374,
        "velmagRMSE": 71.5316,
        "mixRMSE": 302.9056
    },
    {
        "q": 0.36978422,
        "pmin": 4.07882625,
        "pmax": 38.74651945,
        "zmin": -738.1267443,
        "zmax": 547.00435022,
        "lapse": 4.73928966,
        "esia": 3,
        "essa": 1,
        "thkRMSE": 187.599,
        "velmagRMSE": 129.809,
        "mixRMSE": 317.408
    },
    {
        "q": 0.86749695,
        "pmin": 1.77879381,
        "pmax": 38.03568617,
        "zmin": -573.81681907,
        "zmax": 184.50254228,
        "lapse": 1.45094915,
        "esia": 3,
        "essa": 1,
        "thkRMSE": 192.235,
        "velmagRMSE": 72.8104,
        "mixRMSE": 265.04540000000003
    },
    {
        "q": 0.09103496,
        "pmin": 5.88678943,
        "pmax": 35.25356439,
        "zmin": -790.66530854,
        "zmax": 637.37689914,
        "lapse": 0.9648557,
        "esia": 3,
        "essa": 1,
        "thkRMSE": 234.66,
        "velmagRMSE": 328.424,
        "mixRMSE": 563.084
    },
    {
        "q": 0.71495473,
        "pmin": 4.34675154,
        "pmax": 40.6605319,
        "zmin": -604.29165608,
        "zmax": 463.62081343,
        "lapse": 3.09347033,
        "esia": 3,
        "essa": 1,
        "thkRMSE": 185.498,
        "velmagRMSE": 72.5189,
        "mixRMSE": 258.01689999999996
    },
    {
        "q": 0.42403987,
        "pmin": 11.02331312,
        "pmax": 36.52525828,
        "zmin": -404.21994964,
        "zmax": 686.40517856,
        "lapse": 2.48484592,
        "esia": 3,
        "essa": 1,
        "thkRMSE": 199.135,
        "velmagRMSE": 124.264,
        "mixRMSE": 323.399
    },
    {
        "q": 0.45713283,
        "pmin": 3.7431826,
        "pmax": 43.87718879,
        "zmin": -290.67764496,
        "zmax": 365.86478449,
        "lapse": 3.72221696,
        "esia": 3,
        "essa": 1,
        "thkRMSE": 190.582,
        "velmagRMSE": 137.091,
        "mixRMSE": 327.673
    },
    {
        "q": 0.39743922,
        "pmin": 9.31484256,
        "pmax": 42.44715866,
        "zmin": -910.64484907,
        "zmax": 597.33138032,
        "lapse": 2.98562212,
        "esia": 3,
        "essa": 1,
        "thkRMSE": 188.387,
        "velmagRMSE": 77.6749,
        "mixRMSE": 266.0619
    },
    {
        "q": 0.76219534,
        "pmin": 7.22786492,
        "pmax": 40.74390356,
        "zmin": -382.90889293,
        "zmax": 96.76868599,
        "lapse": 0.54370593,
        "esia": 3,
        "essa": 1,
        "thkRMSE": 204.32,
        "velmagRMSE": 72.1283,
        "mixRMSE": 276.4483
    },
    {
        "q": 0.94210246,
        "pmin": 1.10480203,
        "pmax": 38.86547338,
        "zmin": -349.52779975,
        "zmax": 782.05381552,
        "lapse": 0.87696512,
        "esia": 3,
        "essa": 1,
        "thkRMSE": 224.739,
        "velmagRMSE": 75.5764,
        "mixRMSE": 300.3154
    },
    {
        "q": 0.31479828,
        "pmin": 10.94496989,
        "pmax": 41.65688518,
        "zmin": -834.19134103,
        "zmax": 485.02269366,
        "lapse": 1.50389882,
        "esia": 3,
        "essa": 1,
        "thkRMSE": 196.507,
        "velmagRMSE": 123.773,
        "mixRMSE": 320.28
    },
    {
        "q": 0.27486986,
        "pmin": 14.29903612,
        "pmax": 44.62898688,
        "zmin": -760.60674648,
        "zmax": 206.15210487,
        "lapse": 1.69111577,
        "esia": 3,
        "essa": 1,
        "thkRMSE": 191.207,
        "velmagRMSE": 81.114,
        "mixRMSE": 272.321
    },
    {
        "q": 0.90827601,
        "pmin": 0.11803692,
        "pmax": 36.09996194,
        "zmin": -642.07708475,
        "zmax": 69.47301093,
        "lapse": 2.11066566,
        "esia": 3,
        "essa": 1,
        "thkRMSE": 186.542,
        "velmagRMSE": 74.4058,
        "mixRMSE": 260.94780000000003
    },
    {
        "q": 0.13416067,
        "pmin": 5.29327898,
        "pmax": 43.3153166,
        "zmin": -985.70381964,
        "zmax": 118.61542617,
        "lapse": 4.41200774,
        "esia": 3,
        "essa": 1,
        "thkRMSE": 185.501,
        "velmagRMSE": 225.927,
        "mixRMSE": 411.428
    },
    {
        "q": 0.42875,
        "pmin": 15.0,
        "pmax": 45.0,
        "zmin": -743.68,
        "zmax": 197.41,
        "lapse": 1.4795,
        "esia": 3.0023,
        "essa": 0.1,
        "thkRMSE": 200.653,
        "velmagRMSE": 74.6509,
        "mixRMSE": 275.3039
    },
    {
        "q": 0.4188,
        "pmin": 15.0,
        "pmax": 45.0,
        "zmin": -968.75,
        "zmax": 5.3812,
        "lapse": 4.8507,
        "esia": 2.9988,
        "essa": 2.0,
        "thkRMSE": 179.647,
        "velmagRMSE": 76.0431,
        "mixRMSE": 255.69009999999997
    },
    {
        "q": 0.41657,
        "pmin": 15.0,
        "pmax": 45.0,
        "zmin": -898.56,
        "zmax": 12.783,
        "lapse": 5.0,
        "esia": 3.3819,
        "essa": 0.71779,
        "thkRMSE": 183.318,
        "velmagRMSE": 75.9451,
        "mixRMSE": 259.2631
    },
    {
        "q": 0.42282,
        "pmin": 15.0,
        "pmax": 45.0,
        "zmin": -596.57,
        "zmax": 38.065,
        "lapse": 1.7762,
        "esia": 2.6216,
        "essa": 1.4997,
        "thkRMSE": 183.577,
        "velmagRMSE": 74.0054,
        "mixRMSE": 257.5824
    },
    {
        "q": 0.83469,
        "pmin": 0.0,
        "pmax": 45.0,
        "zmin": -908.35,
        "zmax": 516.42,
        "lapse": 4.8393,
        "esia": 3.1603,
        "essa": 1.1638,
        "thkRMSE": 180.082,
        "velmagRMSE": 77.9258,
        "mixRMSE": 258.0078
    },
    {
        "q": 0.84475,
        "pmin": 0.0,
        "pmax": 45.0,
        "zmin": -752.08,
        "zmax": 266.91,
        "lapse": 4.4546,
        "esia": 2.4505,
        "essa": 1.1375,
        "thkRMSE": 176.982,
        "velmagRMSE": 76.8672,
        "mixRMSE": 253.8492
    },
    {
        "q": 0.85274,
        "pmin": 1.7962,
        "pmax": 45.0,
        "zmin": -747.55,
        "zmax": 6.6509,
        "lapse": 4.5413,
        "esia": 3.6378,
        "essa": 1.2365,
        "thkRMSE": 180.569,
        "velmagRMSE": 77.1738,
        "mixRMSE": 257.7428
    },
    {
        "q": 0.97782,
        "pmin": 12.515,
        "pmax": 45.0,
        "zmin": -1000.0,
        "zmax": 45.849,
        "lapse": 5.0,
        "esia": 2.6667,
        "essa": 1.1005,
        "thkRMSE": 175.753,
        "velmagRMSE": 78.2654,
        "mixRMSE": 254.01839999999999
    },
    {
        "q": 1.0,
        "pmin": 7.6875,
        "pmax": 46.0,
        "zmin": -147.76,
        "zmax": 847.95,
        "lapse": 4.2724,
        "esia": 2.4597,
        "essa": 2.0,
        "thkRMSE": 182.329,
        "velmagRMSE": 79.342,
        "mixRMSE": 261.671
    },
    {
        "q": 1.0,
        "pmin": 7.4832,
        "pmax": 46.0,
        "zmin": -170.89,
        "zmax": 915.86,
        "lapse": 4.3737,
        "esia": 3.9085,
        "essa": 1.5112,
        "thkRMSE": 188.108,
        "velmagRMSE": 84.316,
        "mixRMSE": 272.424
    },
    {
        "q": 0.89909,
        "pmin": 13.421,
        "pmax": 46.0,
        "zmin": -940.56,
        "zmax": 135.4,
        "lapse": 5.0,
        "esia": 3.9766,
        "essa": 2.0,
        "thkRMSE": 179.487,
        "velmagRMSE": 77.2867,
        "mixRMSE": 256.77369999999996
    },
    {
        "q": 0.79079,
        "pmin": 12.307,
        "pmax": 46.0,
        "zmin": -65.676,
        "zmax": 237.85,
        "lapse": 3.0333,
        "esia": 1.4684,
        "essa": 1.234,
        "thkRMSE": 176.666,
        "velmagRMSE": 76.312,
        "mixRMSE": 252.978
    },
    {
        "q": 0.63218,
        "pmin": 12.272,
        "pmax": 35.0,
        "zmin": -724.12,
        "zmax": 414.87,
        "lapse": 3.7777,
        "esia": 3.0042,
        "essa": 2.0,
        "thkRMSE": 182.718,
        "velmagRMSE": 81.908,
        "mixRMSE": 264.626
    },
    {
        "q": 0.67741,
        "pmin": 9.8441,
        "pmax": 35.0,
        "zmin": -592.42,
        "zmax": 339.89,
        "lapse": 4.9636,
        "esia": 3.2841,
        "essa": 0.1,
        "thkRMSE": 188.039,
        "velmagRMSE": 84.073,
        "mixRMSE": 272.11199999999997
    },
    {
        "q": 0.84511,
        "pmin": 7.017,
        "pmax": 46.0,
        "zmin": -681.03,
        "zmax": 824.58,
        "lapse": 5.0,
        "esia": 1.0,
        "essa": 0.9988,
        "thkRMSE": 173.262,
        "velmagRMSE": 82.9308,
        "mixRMSE": 256.19280000000003
    },
    {
        "q": 0.68189,
        "pmin": 10.267,
        "pmax": 40.823,
        "zmin": -608.88,
        "zmax": 327.03,
        "lapse": 4.9129,
        "esia": 2.909,
        "essa": 2.0,
        "thkRMSE": 179.026,
        "velmagRMSE": 79.9164,
        "mixRMSE": 258.9424
    },
    {
        "q": 0.71934,
        "pmin": 9.8223,
        "pmax": 46.0,
        "zmin": -596.75,
        "zmax": 529.67,
        "lapse": 2.0192,
        "esia": 3.0615,
        "essa": 0.1,
        "thkRMSE": 197.23,
        "velmagRMSE": 73.2551,
        "mixRMSE": 270.4851
    },
    {
        "q": 0.67151,
        "pmin": 8.9446,
        "pmax": 46.0,
        "zmin": -690.36,
        "zmax": 250.32,
        "lapse": 2.4623,
        "esia": 1.9317,
        "essa": 2.0,
        "thkRMSE": 176.034,
        "velmagRMSE": 77.5367,
        "mixRMSE": 253.5707
    },
    {
        "q": 1.0,
        "pmin": 6.4074,
        "pmax": 46.0,
        "zmin": -362.54,
        "zmax": 0.0,
        "lapse": 2.5183,
        "esia": 1.5745,
        "essa": 1.1229,
        "thkRMSE": 173.057,
        "velmagRMSE": 78.4263,
        "mixRMSE": 251.48329999999999
    },
    {
        "q": 0.71018,
        "pmin": 10.242,
        "pmax": 46.0,
        "zmin": -648.57,
        "zmax": 584.24,
        "lapse": 1.9083,
        "esia": 3.3118,
        "essa": 0.9046,
        "thkRMSE": 190.519,
        "velmagRMSE": 72.3025,
        "mixRMSE": 262.8215
    },
    {
        "q": 0.41299,
        "pmin": 9.9604,
        "pmax": 46.0,
        "zmin": -947.47,
        "zmax": 142.77,
        "lapse": 4.0228,
        "esia": 1.501,
        "essa": 1.0735,
        "thkRMSE": 175.371,
        "velmagRMSE": 80.4239,
        "mixRMSE": 255.7949
    },
    {
        "q": 0.40299,
        "pmin": 9.3546,
        "pmax": 46.0,
        "zmin": -978.92,
        "zmax": 123.1,
        "lapse": 1.8554,
        "esia": 4.2752,
        "essa": 2.0,
        "thkRMSE": 194.617,
        "velmagRMSE": 75.1028,
        "mixRMSE": 269.71979999999996
    },
    {
        "q": 0.85065,
        "pmin": 12.72,
        "pmax": 46.0,
        "zmin": -963.21,
        "zmax": 746.5,
        "lapse": 4.5393,
        "esia": 1.2282,
        "essa": 2.0,
        "thkRMSE": 172.58,
        "velmagRMSE": 84.3009,
        "mixRMSE": 256.8809
    },
    {
        "q": 0.67242,
        "pmin": 5.7228,
        "pmax": 46.0,
        "zmin": -333.44,
        "zmax": 0.0,
        "lapse": 4.5136,
        "esia": 1.0,
        "essa": 1.1147,
        "thkRMSE": 173.46,
        "velmagRMSE": 83.3937,
        "mixRMSE": 256.8537
    },
    {
        "q": 0.62848,
        "pmin": 0.82434,
        "pmax": 46.0,
        "zmin": -979.12,
        "zmax": 788.05,
        "lapse": 4.4873,
        "esia": 1.0,
        "essa": 2.0,
        "thkRMSE": 185.489,
        "velmagRMSE": 80.0735,
        "mixRMSE": 265.5625
    },
    {
        "q": 1.0,
        "pmin": 6.4079,
        "pmax": 46.0,
        "zmin": -1000.0,
        "zmax": 40.194,
        "lapse": 4.6352,
        "esia": 1.0,
        "essa": 2.0,
        "thkRMSE": 170.387,
        "velmagRMSE": 87.1263,
        "mixRMSE": 257.5133
    },
    {
        "q": 1.0,
        "pmin": 14.999,
        "pmax": 46.0,
        "zmin": -582.74,
        "zmax": 590.15,
        "lapse": 3.5484,
        "esia": 1.0,
        "essa": 2.0,
        "thkRMSE": 171.232,
        "velmagRMSE": 83.969,
        "mixRMSE": 255.201
    },
    {
        "q": 1.0,
        "pmin": 1.1742,
        "pmax": 46.0,
        "zmin": -685.35,
        "zmax": 517.43,
        "lapse": 4.5485,
        "esia": 1.0,
        "essa": 2.0,
        "thkRMSE": 171.817,
        "velmagRMSE": 82.5933,
        "mixRMSE": 254.4103
    },
    {
        "q": 0.63657,
        "pmin": 1.2176,
        "pmax": 46.0,
        "zmin": -978.21,
        "zmax": 982.29,
        "lapse": 5.0,
        "esia": 4.4957,
        "essa": 1.901,
        "thkRMSE": 186.818,
        "velmagRMSE": 87.8702,
        "mixRMSE": 274.6882
    },
    {
        "q": 0.90274,
        "pmin": 11.774,
        "pmax": 46.0,
        "zmin": -731.56,
        "zmax": 156.97,
        "lapse": 3.8304,
        "esia": 1.0,
        "essa": 1.3281,
        "thkRMSE": 171.143,
        "velmagRMSE": 86.1818,
        "mixRMSE": 257.3248
    },
    {
        "q": 1.0,
        "pmin": 0.53997,
        "pmax": 46.0,
        "zmin": -654.15,
        "zmax": 521.74,
        "lapse": 5.0,
        "esia": 5.0,
        "essa": 2.0,
        "thkRMSE": 185.23,
        "velmagRMSE": 79.7955,
        "mixRMSE": 265.02549999999997
    },
    {
        "q": 0.63914,
        "pmin": 15.0,
        "pmax": 46.0,
        "zmin": -366.4,
        "zmax": 594.3,
        "lapse": 3.4681,
        "esia": 1.0,
        "essa": 1.2225,
        "thkRMSE": 175.453,
        "velmagRMSE": 79.1094,
        "mixRMSE": 254.5624
    },
    {
        "q": 0.9506,
        "pmin": 2.8176,
        "pmax": 46.0,
        "zmin": -612.1706,
        "zmax": 231.7791,
        "lapse": 1.1917,
        "esia": 2.9688,
        "essa": 1.0876,
        "thkRMSE": 190.142,
        "velmagRMSE": 72.6927,
        "mixRMSE": 262.8347
    },
    {
        "q": 0.918,
        "pmin": 3.2369,
        "pmax": 46.0,
        "zmin": -549.6891,
        "zmax": 496.5741,
        "lapse": 5.0,
        "esia": 2.134,
        "essa": 1.3024,
        "thkRMSE": 176.006,
        "velmagRMSE": 76.9505,
        "mixRMSE": 252.9565
    },
    {
        "q": 0.9363,
        "pmin": 4.217,
        "pmax": 46.0,
        "zmin": -381.9825,
        "zmax": 662.3751,
        "lapse": 0.9628,
        "esia": 2.6362,
        "essa": 1.0697,
        "thkRMSE": 200.64,
        "velmagRMSE": 70.423,
        "mixRMSE": 271.063
    },
    {
        "q": 1.0,
        "pmin": 15.0,
        "pmax": 46.0,
        "zmin": -572.9925,
        "zmax": 708.6983,
        "lapse": 5.0,
        "esia": 5.0,
        "essa": 1.0644,
        "thkRMSE": 186.371,
        "velmagRMSE": 83.8436,
        "mixRMSE": 270.2146
    },
    {
        "q": 0.60537,
        "pmin": 3.3531,
        "pmax": 46.0,
        "zmin": -714.36,
        "zmax": 494.83,
        "lapse": 2.5213,
        "esia": 1.0,
        "essa": 1.4901,
        "thkRMSE": 175.51,
        "velmagRMSE": 77.6987,
        "mixRMSE": 253.2087
    },
    {
        "q": 0.3273,
        "pmin": 15.0,
        "pmax": 46.0,
        "zmin": -809.46,
        "zmax": 0.0,
        "lapse": 4.6251,
        "esia": 3.4314,
        "essa": 2.0,
        "thkRMSE": 181.716,
        "velmagRMSE": 76.3955,
        "mixRMSE": 258.1115
    },
    {
        "q": 1.0,
        "pmin": 15.0,
        "pmax": 46.0,
        "zmin": -754.57,
        "zmax": 871.67,
        "lapse": 4.434,
        "esia": 1.0,
        "essa": 2.0,
        "thkRMSE": 171.426,
        "velmagRMSE": 84.0817,
        "mixRMSE": 255.5077
    },
    {
        "q": 0.86617,
        "pmin": 7.5651,
        "pmax": 46.0,
        "zmin": -212.13,
        "zmax": 534.72,
        "lapse": 4.4734,
        "esia": 2.7805,
        "essa": 1.005,
        "thkRMSE": 182.379,
        "velmagRMSE": 77.1802,
        "mixRMSE": 259.5592
    },
    {
        "q": 1.0,
        "pmin": 9.8301,
        "pmax": 46.0,
        "zmin": -1000.0,
        "zmax": 676.98,
        "lapse": 5.0,
        "esia": 5.0,
        "essa": 1.1116,
        "thkRMSE": 185.881,
        "velmagRMSE": 84.7114,
        "mixRMSE": 270.5924
    },
    {
        "q": 0.64443,
        "pmin": 15.0,
        "pmax": 46.0,
        "zmin": -314.24,
        "zmax": 983.72,
        "lapse": 5.0,
        "esia": 5.0,
        "essa": 2.0,
        "thkRMSE": 188.557,
        "velmagRMSE": 90.5294,
        "mixRMSE": 279.08639999999997
    },
    {
        "q": 0.66813,
        "pmin": 0.0,
        "pmax": 46.0,
        "zmin": -776.76,
        "zmax": 453.89,
        "lapse": 5.0,
        "esia": 5.0,
        "essa": 1.0186,
        "thkRMSE": 188.909,
        "velmagRMSE": 82.9501,
        "mixRMSE": 271.8591
    },
    {
        "q": 0.65422,
        "pmin": 4.6365,
        "pmax": 46.0,
        "zmin": -459.74,
        "zmax": 6.7135,
        "lapse": 5.0,
        "esia": 5.0,
        "essa": 1.1822,
        "thkRMSE": 187.841,
        "velmagRMSE": 84.8849,
        "mixRMSE": 272.7259
    },
    {
        "q": 0.40267,
        "pmin": 15.0,
        "pmax": 46.0,
        "zmin": -782.9,
        "zmax": 435.76,
        "lapse": 4.4315,
        "esia": 1.0,
        "essa": 1.6369,
        "thkRMSE": 174.622,
        "velmagRMSE": 83.2211,
        "mixRMSE": 257.84310000000005
    },
    {
        "q": 0.85747,
        "pmin": 9.6049,
        "pmax": 46.0,
        "zmin": -993.97,
        "zmax": 131.67,
        "lapse": 5.0,
        "esia": 4.5356,
        "essa": 1.1235,
        "thkRMSE": 183.786,
        "velmagRMSE": 80.9301,
        "mixRMSE": 264.7161
    },
    {
        "q": 0.35485,
        "pmin": 14.316,
        "pmax": 43.078,
        "zmin": -832.49,
        "zmax": 31.389,
        "lapse": 0.40472,
        "esia": 2.3077,
        "essa": 1.117,
        "thkRMSE": 192.261,
        "velmagRMSE": 85.1605,
        "mixRMSE": 277.4215
    },
    {
        "q": 1.0,
        "pmin": 4.3628,
        "pmax": 46.0,
        "zmin": -419.75,
        "zmax": 145.85,
        "lapse": 3.501,
        "esia": 1.0,
        "essa": 2.0,
        "thkRMSE": 171.105,
        "velmagRMSE": 83.5014,
        "mixRMSE": 254.6064
    },
    {
        "q": 1.0,
        "pmin": 0.0,
        "pmax": 43.2,
        "zmin": -1000.0,
        "zmax": 0.0,
        "lapse": 3.6261,
        "esia": 3.253,
        "essa": 1.1735,
        "thkRMSE": 179.714,
        "velmagRMSE": 77.2215,
        "mixRMSE": 256.9355
    },
    {
        "q": 1.0,
        "pmin": 10.92,
        "pmax": 43.886,
        "zmin": -502.6,
        "zmax": 24.337,
        "lapse": 5.0,
        "esia": 1.0,
        "essa": 2.0,
        "thkRMSE": 170.696,
        "velmagRMSE": 86.1802,
        "mixRMSE": 256.8762
    },
    {
        "q": 0.67005,
        "pmin": 10.679,
        "pmax": 46.0,
        "zmin": -654.52,
        "zmax": 383.12,
        "lapse": 1.7513,
        "esia": 3.55,
        "essa": 2.0,
        "thkRMSE": 189.482,
        "velmagRMSE": 72.8646,
        "mixRMSE": 262.34659999999997
    },
    {
        "q": 0.65377,
        "pmin": 15.0,
        "pmax": 42.524,
        "zmin": -533.67,
        "zmax": 95.885,
        "lapse": 5.0,
        "esia": 1.8319,
        "essa": 1.0038,
        "thkRMSE": 175.432,
        "velmagRMSE": 82.5199,
        "mixRMSE": 257.9519
    },
    {
        "q": 0.6895,
        "pmin": 9.9197,
        "pmax": 40.852,
        "zmin": -658.23,
        "zmax": 453.14,
        "lapse": 1.7085,
        "esia": 3.3789,
        "essa": 0.1,
        "thkRMSE": 204.199,
        "velmagRMSE": 74.3043,
        "mixRMSE": 278.5033
    },
    {
        "q": 0.5837,
        "pmin": 15.0,
        "pmax": 46.0,
        "zmin": -845.07,
        "zmax": 1.3194,
        "lapse": 1.4566,
        "esia": 1.0,
        "essa": 2.0,
        "thkRMSE": 173.318,
        "velmagRMSE": 84.6426,
        "mixRMSE": 257.9606
    },
    {
        "q": 0.47627,
        "pmin": 9.3947,
        "pmax": 46.0,
        "zmin": -922.81,
        "zmax": 513.95,
        "lapse": 1.4145,
        "esia": 3.1333,
        "essa": 2.0,
        "thkRMSE": 191.233,
        "velmagRMSE": 75.3576,
        "mixRMSE": 266.5906
    },
    {
        "q": 0.56163,
        "pmin": 0.0,
        "pmax": 46.0,
        "zmin": -1000.0,
        "zmax": 218.81,
        "lapse": 3.3542,
        "esia": 3.1696,
        "essa": 1.1982,
        "thkRMSE": 183.072,
        "velmagRMSE": 74.5606,
        "mixRMSE": 257.6326
    },
    {
        "q": 0.68148,
        "pmin": 15.0,
        "pmax": 46.0,
        "zmin": 0.0,
        "zmax": 164.74,
        "lapse": 3.5056,
        "esia": 3.1017,
        "essa": 2.0,
        "thkRMSE": 183.389,
        "velmagRMSE": 77.694,
        "mixRMSE": 261.083
    },
    {
        "q": 0.61752,
        "pmin": 3.7516,
        "pmax": 46.0,
        "zmin": -779.45,
        "zmax": 855.83,
        "lapse": 1.7534,
        "esia": 3.0676,
        "essa": 0.93767,
        "thkRMSE": 195.628,
        "velmagRMSE": 69.1897,
        "mixRMSE": 264.8177
    },
    {
        "q": 1.0,
        "pmin": 15.0,
        "pmax": 46.0,
        "zmin": 0.0,
        "zmax": 207.58,
        "lapse": 2.3787,
        "esia": 2.9997,
        "essa": 1.2379,
        "thkRMSE": 185.269,
        "velmagRMSE": 75.0179,
        "mixRMSE": 260.2869
    },
    {
        "q": 1.0,
        "pmin": 7.8982,
        "pmax": 46.0,
        "zmin": -674.53,
        "zmax": 0.050614,
        "lapse": 4.9897,
        "esia": 1.0,
        "essa": 2.0,
        "thkRMSE": 170.501,
        "velmagRMSE": 86.685,
        "mixRMSE": 257.18600000000004
    },
    {
        "q": 1.0,
        "pmin": 0.0,
        "pmax": 46.0,
        "zmin": -756.8,
        "zmax": 973.73,
        "lapse": 3.7285,
        "esia": 2.9891,
        "essa": 1.1529,
        "thkRMSE": 183.392,
        "velmagRMSE": 75.4179,
        "mixRMSE": 258.80989999999997
    },
    {
        "q": 1.0,
        "pmin": 9.4685,
        "pmax": 46.0,
        "zmin": -88.874,
        "zmax": 183.56,
        "lapse": 2.0989,
        "esia": 1.0,
        "essa": 2.0,
        "thkRMSE": 173.917,
        "velmagRMSE": 78.5595,
        "mixRMSE": 252.4765
    },
    {
        "q": 1.0,
        "pmin": 15.0,
        "pmax": 46.0,
        "zmin": 0.0,
        "zmax": 1000.0,
        "lapse": 3.2753,
        "esia": 1.0,
        "essa": 2.0,
        "thkRMSE": 177.028,
        "velmagRMSE": 80.7328,
        "mixRMSE": 257.7608
    },
    {
        "q": 0.46462,
        "pmin": 4.4531,
        "pmax": 46.0,
        "zmin": -1000.0,
        "zmax": 74.987,
        "lapse": 1.3798,
        "esia": 1.0,
        "essa": 2.0,
        "thkRMSE": 174.354,
        "velmagRMSE": 83.6532,
        "mixRMSE": 258.0072
    },
    {
        "q": 1.0,
        "pmin": 10.151,
        "pmax": 46.0,
        "zmin": -317.15,
        "zmax": 457.51,
        "lapse": 2.1161,
        "esia": 1.0,
        "essa": 2.0,
        "thkRMSE": 173.629,
        "velmagRMSE": 80.062,
        "mixRMSE": 253.69099999999997
    },
    {
        "q": 0.83035,
        "pmin": 3.7304,
        "pmax": 46.0,
        "zmin": -435.06,
        "zmax": 410.3,
        "lapse": 1.2485,
        "esia": 5.0,
        "essa": 0.1,
        "thkRMSE": 234.965,
        "velmagRMSE": 79.9305,
        "mixRMSE": 314.89549999999997
    },
    {
        "q": 0.68018,
        "pmin": 10.891,
        "pmax": 46.0,
        "zmin": -332.82,
        "zmax": 11.907,
        "lapse": 1.6049,
        "esia": 1.0,
        "essa": 2.0,
        "thkRMSE": 173.494,
        "velmagRMSE": 81.8806,
        "mixRMSE": 255.3746
    },
    {
        "q": 1.0,
        "pmin": 15.0,
        "pmax": 46.0,
        "zmin": -1000.0,
        "zmax": 0.0,
        "lapse": 0.0,
        "esia": 5.0,
        "essa": 1.894,
        "thkRMSE": 249.808,
        "velmagRMSE": 84.9688,
        "mixRMSE": 334.7768
    },
    {
        "q": 1.0,
        "pmin": 0.0,
        "pmax": 46.0,
        "zmin": -994.72,
        "zmax": 940.39,
        "lapse": 4.1077,
        "esia": 5.0,
        "essa": 0.83918,
        "thkRMSE": 191.477,
        "velmagRMSE": 84.4501,
        "mixRMSE": 275.9271
    },
    {
        "q": 1.0,
        "pmin": 12.514,
        "pmax": 46.0,
        "zmin": -57.328,
        "zmax": 633.58,
        "lapse": 3.0277,
        "esia": 3.092,
        "essa": 2.0,
        "thkRMSE": 185.549,
        "velmagRMSE": 75.9931,
        "mixRMSE": 261.5421
    },
    {
        "q": 1.0,
        "pmin": 5.2924,
        "pmax": 46.0,
        "zmin": -1000.0,
        "zmax": 1000.0,
        "lapse": 5.0,
        "esia": 3.1113,
        "essa": 2.0,
        "thkRMSE": 178.031,
        "velmagRMSE": 76.6846,
        "mixRMSE": 254.7156
    },
    {
        "q": 0.51769,
        "pmin": 6.5191,
        "pmax": 46.0,
        "zmin": -632.54,
        "zmax": 25.867,
        "lapse": 1.4755,
        "esia": 3.0412,
        "essa": 1.0939,
        "thkRMSE": 192.716,
        "velmagRMSE": 74.2846,
        "mixRMSE": 267.0006
    },
    {
        "q": 0.53198,
        "pmin": 15.0,
        "pmax": 46.0,
        "zmin": -429.56,
        "zmax": 262.86,
        "lapse": 1.1613,
        "esia": 3.137,
        "essa": 2.0,
        "thkRMSE": 191.664,
        "velmagRMSE": 72.043,
        "mixRMSE": 263.707
    },
    {
        "q": 1.0,
        "pmin": 3.8757,
        "pmax": 46.0,
        "zmin": -257.75,
        "zmax": 722.14,
        "lapse": 1.6203,
        "esia": 3.0837,
        "essa": 1.0838,
        "thkRMSE": 201.416,
        "velmagRMSE": 73.2546,
        "mixRMSE": 274.6706
    },
    {
        "q": 1.0,
        "pmin": 15.0,
        "pmax": 46.0,
        "zmin": -844.38,
        "zmax": 492.58,
        "lapse": 4.9887,
        "esia": 1.0,
        "essa": 2.0,
        "thkRMSE": 170.68,
        "velmagRMSE": 85.5607,
        "mixRMSE": 256.2407
    },
    {
        "q": 1.0,
        "pmin": 5.592,
        "pmax": 46.0,
        "zmin": -236.0,
        "zmax": 516.24,
        "lapse": 2.2369,
        "esia": 3.075,
        "essa": 2.0,
        "thkRMSE": 189.117,
        "velmagRMSE": 73.1499,
        "mixRMSE": 262.26689999999996
    },
    {
        "q": 0.39635,
        "pmin": 15.0,
        "pmax": 46.0,
        "zmin": -950.44,
        "zmax": 481.94,
        "lapse": 0.0,
        "esia": 3.0786,
        "essa": 1.0128,
        "thkRMSE": 221.778,
        "velmagRMSE": 77.6247,
        "mixRMSE": 299.4027
    },
    {
        "q": 0.82256,
        "pmin": 15.0,
        "pmax": 46.0,
        "zmin": -28.181,
        "zmax": 23.181,
        "lapse": 2.0223,
        "esia": 3.056,
        "essa": 2.0,
        "thkRMSE": 184.968,
        "velmagRMSE": 74.0707,
        "mixRMSE": 259.0387
    },
    {
        "q": 0.39519,
        "pmin": 15.0,
        "pmax": 46.0,
        "zmin": -988.07,
        "zmax": 379.15,
        "lapse": 0.05631,
        "esia": 3.0285,
        "essa": 1.0534,
        "thkRMSE": 216.101,
        "velmagRMSE": 76.164,
        "mixRMSE": 292.265
    },
    {
        "q": 0.70705,
        "pmin": 0.0,
        "pmax": 46.0,
        "zmin": -992.33,
        "zmax": 1.273,
        "lapse": 2.0082,
        "esia": 2.8986,
        "essa": 2.0,
        "thkRMSE": 181.499,
        "velmagRMSE": 75.9847,
        "mixRMSE": 257.4837
    },
    {
        "q": 0.71741,
        "pmin": 15.0,
        "pmax": 46.0,
        "zmin": -950.48,
        "zmax": 937.64,
        "lapse": 5.0,
        "esia": 2.9431,
        "essa": 2.0,
        "thkRMSE": 178.604,
        "velmagRMSE": 79.622,
        "mixRMSE": 258.226
    },
    {
        "q": 0.86839,
        "pmin": 8.1103,
        "pmax": 46.0,
        "zmin": -945.97,
        "zmax": 964.77,
        "lapse": 1.3067,
        "esia": 3.041,
        "essa": 2.0,
        "thkRMSE": 190.762,
        "velmagRMSE": 74.9953,
        "mixRMSE": 265.7573
    },
    {
        "q": 1.0,
        "pmin": 15.0,
        "pmax": 46.0,
        "zmin": -1000.0,
        "zmax": 1000.0,
        "lapse": 4.6892,
        "esia": 3.0948,
        "essa": 1.2825,
        "thkRMSE": 178.55,
        "velmagRMSE": 76.581,
        "mixRMSE": 255.13100000000003
    },
    {
        "q": 0.60982,
        "pmin": 4.6994,
        "pmax": 46.0,
        "zmin": -667.31,
        "zmax": 634.58,
        "lapse": 0.86489,
        "esia": 3.0791,
        "essa": 2.0,
        "thkRMSE": 200.375,
        "velmagRMSE": 70.5411,
        "mixRMSE": 270.91610000000003
    },
    {
        "q": 0.83618,
        "pmin": 15.0,
        "pmax": 46.0,
        "zmin": -763.45,
        "zmax": 229.33,
        "lapse": 4.6797,
        "esia": 1.0,
        "essa": 2.0,
        "thkRMSE": 171.605,
        "velmagRMSE": 87.6475,
        "mixRMSE": 259.2525
    }
]